mercedesSFMConnector/__init__.py
mercedesSFMConnector/api/__init__.py
mercedesSFMConnector/api/external_values.py
mercedesSFMConnector/api/measure_groups.py
mercedesSFMConnector/api/measures.py
mercedesSFMConnector/token_handler/__init__.py
mercedesSFMConnector/token_handler/token_libs.py
mercedesSFMConnector-0.1.5.dist-info/METADATA
mercedesSFMConnector-0.1.5.dist-info/WHEEL
mercedesSFMConnector-0.1.5.dist-info/top_level.txt
mercedesSFMConnector-0.1.5.dist-info/RECORD
