Metadata-Version: 2.1
Name: mercedesSFMConnector
Version: 0.1.5
Summary: A library to interact with the Mercedes SFM API in Python
Author: Ethan Wilkes
License: MIT
Platform: UNKNOWN
Requires-Dist: requests
Requires-Dist: requests-oauthlib
Requires-Dist: oauthlib
